{
    "keyboard_name": "macropad_3x3",
    "maintainer": "jfdona23",
    "manufacturer": "jfdona23",
    "url": "https://jfdonadio.com",
    "usb": {
        "vid": "0x03EB",
        "pid": "0x2042",
        "device_version": "0.0.1"
    },
    "development_board": "promicro",
    "bootloader": "caterina",
    "diode_direction": "COL2ROW",
    "matrix_pins": {
        "cols": ["F4", "F5", "F6"],
        "rows": ["D1", "D4", "D0"]
    },
    "layouts": {
        "LAYOUT": {
            "layout": [
                { "matrix": [0, 0], "x": 0, "y": 0 },
                { "matrix": [0, 1], "x": 1, "y": 0 },
                { "matrix": [0, 2], "x": 2, "y": 0 },
                { "matrix": [1, 0], "x": 0, "y": 1 },
                { "matrix": [1, 1], "x": 1, "y": 1 },
                { "matrix": [1, 2], "x": 2, "y": 1 },
                { "matrix": [2, 0], "x": 0, "y": 2 },
                { "matrix": [2, 1], "x": 1, "y": 2 },
                { "matrix": [2, 2], "x": 2, "y": 2 }
            ]
        }
    }
}